{
    "categories": [
        {
            "id": "1",
            "url": "#",
            "text": "01觀點"
        },
        {
            "id": "2",
            "url": "#",
            "text": "01博評"
        },
        {
            "id": "3",
            "url": "#",
            "text": "社區"
        },
        {
            "id": "4",
            "url": "#",
            "text": "娛樂"
        },
        {
            "id": "5",
            "url": "#",
            "text": "韓國大選"
        },
        {
            "id": "6",
            "url": "#",
            "text": "國際"
        },
        {
            "id": "7",
            "url": "#",
            "text": "女生"
        },
        {
            "id": "8",
            "url": "#",
            "text": "藝術3月"
        },
        {
            "id": "9",
            "url": "#",
            "text": "藝文創意"
        },
        {
            "id": "10",
            "url": "#",
            "text": "體育"
        },
        {
            "id": "11",
            "url": "#",
            "text": "熱話"
        },
        {
            "id": "12",
            "url": "#",
            "text": "科技玩物"
        },
        {
            "id": "13",
            "url": "#",
            "text": "01哲學"
        },
        {
            "id": "14",
            "url": "#",
            "text": "武備志"
        },
        {
            "id": "15",
            "url": "#",
            "text": "一物"
        },
        {
            "id": "16",
            "url": "#",
            "text": "01影像"
        },
        {
            "id": "17",
            "url": "#",
            "text": "01活動"
        },
        {
            "id": "18",
            "url": "#",
            "text": "01空間"
        },
        {
            "id": "19",
            "url": "#",
            "text": "01空間2"
        },
        {
            "id": "20",
            "url": "#",
            "text": "01空間3"
        },
        {
            "id": "21",
            "url": "#",
            "text": "01空間4"
        },
        {
            "id": "22",
            "url": "#",
            "text": "01空間5"
        },
        {
            "id": "23",
            "url": "#",
            "text": "01空間6"
        },
        {
            "id": "24",
            "url": "#",
            "text": "會員專區"
        }
    ],

    "articles": [
        {
            "id": "1",
            "image": "https://cdn.hk01.com/media/article/87004/thumbnail/7607c287a33dd8e3723c2d7918011513.jpg",
            "title": "【01百科】捐款給慈善機構後　申請扣稅四大注意事項",
            "preview": "政府為支援慈善機構發展，其中一項措施，是容許善心捐款人豁免繳交部分稅款。審計署最新統計，現時全港有近9,000間稅務局註冊慈善機構，較10年前激增近倍。不過要注意，並非所有「志願」……",
            "url": "#"
        },
        {
            "id": "2",
            "image": "https://cdn.hk01.com/media/article/87010/thumbnail/4dade380b251ebf8cbbada534fbe1f79.jpg",
            "title": "有線注資方案待股東批准　吳天海︰相信通過機會唔低",
            "preview": "有線寬頻（1097）主席兼行政總裁吳天海預期，有線在5月29日將會舉行特別股東大會。他相信，新注資方案會得到小股東的過半數支持機會「唔低」。",
            "url": "#"
        },
        {
            "id": "3",
            "image": "https://cdn.hk01.com/media/article/86985/thumbnail/61e6f0e04cb7c553685ac1b619c61ab0.jpg",
            "title": "【官場貪污．博評】美國還有多少郭文貴式「定時炸彈」？",
            "preview": "中共十九大前夕郭文貴的爆料在北京引發的震蕩是巨大的，就結局而言只能是一時的風波，不可能造成「核摧毀」，帶出的反而是郭文貴會不會成為第二個李志綏、海外究竟還有多少郭文貴式「定時炸彈」……",
            "url": "#"
        },
        {
            "id": "4",
            "image": "https://cdn.hk01.com/media/article/86986/thumbnail/9baba95f2b404fc9d0bdd53d0ff0b23b.jpg",
            "title": "【多圖】相較「遼寧艦」　中國首艘國產航母有三大優勢",
            "preview": "中國第二艘航空母艦今日（26日）在大連下水，這也是中國第一艘自行建造的航母。而中國第一艘航母「遼寧號」船體購自烏克蘭，前身系前蘇聯未建造完工的航母「瓦良格號」。據悉，001……",
            "url": "#"
        },
        {
            "id": "5",
            "image": "https://cdn.hk01.com/media/article/87006/thumbnail/64654af20605d63bf5f6f9be183cf1aa.jpg",
            "title": "不只谷阿莫！ 金庸告內地作家江南「同人創作」侵權求償500萬",
            "preview": "《此間的少年》是江南早年的作品，以宋代為背景，講述了「汴京大學」裡喬峰、令狐沖、黃蓉等人的故事。早前江南本人也承認《此間的少年》中的人物姓名來自金庸作品。此「同人創作」引起金庸不滿……",
            "url": "#"
        },
        {
            "id": "6",
            "image": "https://cdn.hk01.com/media/article/87001/thumbnail/71faabe10c5cfebc747c3bcbf5e9fc05.jpg",
            "title": "有線股東會變「申訴會 」　散戶炮轟︰無息派　要多包糖都唔得？",
            "preview": "有線寬頻（1097）舉行股東大會，小股東除了批評公司供股手法之外，亦有小股東批評「招呼不佳」，直指「連要多杯咖啡都唔畀！」有線小股東會上大控訴，楊女士批評有線寬頻的服務「好……",
            "url": "#"
        },
        {
            "id": "7",
            "image": "https://cdn.hk01.com/media/article/86993/thumbnail/bce75ac0e1353e2e64bbda5d51c23ec8.jpg",
            "title": "發展局長座駕被爆竊　警拘捕兩雙程證男　文件丟噴水池",
            "preview": "發展局局長馬紹祥座駕「AM9」昨日晚上被人打破玻璃窗盜去財物，發展局證實車上公事包、平板電腦及少量政府文件被盜。據了解，警方今日（4日26日）拘捕兩名持雙程證男子，當中一人涉現場「……",
            "url": "#"
        },
        {
            "id": "8",
            "image": "https://cdn.hk01.com/media/article/86995/thumbnail/2f6681a37728525925026388e3ee0277.jpg",
            "title": "【斧劫七仔】8日3劫便利店　越南籍斧頭賊落網",
            "preview": "據知，該名斧頭賊獨自犯案，最近一次犯案，是於昨晚（25日）凌晨約3時，到旺角打劫位於界限街14號地下轉角位的7-11便利店，兩名女店員突然被一位「由頭黑到落腳」，身穿黑衫黑褲、戴黑……",
            "url": "#"
        },
        {
            "id": "9",
            "image": "https://cdn.hk01.com/media/article/86954/thumbnail/91607d2c396119af5b3f93d4880e49e1.jpg",
            "title": "Samsung Pay攻港　支援終端機覆蓋率料逾9成",
            "preview": "這兩年先後有不少手機支付攻港，包括較廣為人知的Apple Pay和Android Pay，三星電子香港預告將在本季內推出Samsung Pay，而由今日開始至5月24日會推出體驗計……",
            "url": "#"
        },
        {
            "id": "10",
            "image": "https://cdn.hk01.com/media/article/87003/thumbnail/86c7500e34dd559aafd2708ad8cff66b.jpg",
            "title": "受惠貸款減值減少　渣打首季稅前溢利大升98%",
            "preview": "渣打集團﹙2888﹚公布，截至今年3月底首季除稅前法定溢利為9.9億﹙美元‧下同﹚，按年上升98%；而去年第四季則錄得8.71億元的虧損。溢利反彈，一來因為經營收入增長8%……",
            "url": "#"
        },
        {
            "id": "11",
            "image": "https://cdn.hk01.com/media/article/86931/thumbnail/3dba171e256d9abb4b81f32c71d1a78c.jpg",
            "title": "非法集結被捕准保釋　周五提堂　梁頌恆：現階段認罪機會低",
            "preview": "梁頌恆、游蕙禎涉嫌於去年11月在立法會宣誓被裁決無效後，衝入會議室，被控非法集結及強行進入的交替控罪。兩人今早約7時被警方上門拘捕，下午約3時獲准保釋離開中區警署。游蕙禎表……",
            "url": "#"
        },
        {
            "id": "12",
            "image": "https://cdn.hk01.com/media/article/86839/thumbnail/4770a6e933f132cb33b1c856ac05f6c2.jpg",
            "title": "遊行隊伍的公公婆婆，是我城的西西弗",
            "preview": "剛過去的星期日，有一個名為「反對小圈特首，抗議政治逼害」遊行，大概沒有幾多人有留意。儘管這半年民選議員被DQ、被控告的事接二連三，政府又視錢財如糞土般借發展為名供養官商鄉黑，甚至漠……",
            "url": "#"
        },
        {
            "id": "13",
            "image": "https://cdn.hk01.com/media/article/86943/thumbnail/91c29ca3e8800ce4bed0a2c593a72df5.jpg",
            "title": "林鄭化妝費僅葉劉兩成　星級化妝師：無畀折頭林太",
            "preview": "特首參選人近日陸續向選舉事務處申報選舉開支，成功當選的林鄭月娥共籌得經費約1,870萬元，競選總開支約為1,260萬元。文件顯示，林鄭月娥在「個人開支」方面，3次化妝費用為4,18……",
            "url": "#"
        },
        {
            "id": "14",
            "image": "https://cdn.hk01.com/media/article/86961/thumbnail/a5b136fc592e93e612def4793986e68c.jpg",
            "title": "林鄭公關大員月薪約14萬　葉劉批太貴：競選團隊可能想「鑿一筆",
            "preview": "屢爆「關公災難」特首參選人近日陸續向選舉事務處申報選舉開支，成功當選的林鄭月娥共籌得經費約1,870萬元，競選總開支約為1,260萬元。文件顯示，林鄭月娥的代理人及選舉助理……",
            "url": "#"
        },
        {
            "id": "15",
            "image": "https://cdn.hk01.com/media/article/86935/thumbnail/1ed93381b407fc8773881aaff5b1cbde.jpg",
            "title": "持刀綁保安　賊幫闖會德豐地盤偷CPU、RAM　四漢被",
            "preview": "涉事地盤為會德豐地產於屯門掃管笏的住宅項目「NAPA」，項目預計於明年落成。地盤內有兩個臨時辦公室，平日於凌晨時分皆會有兩名保安員駐守。今日凌晨12時15分左右，三名盜賊潛入地盤辦……",
            "url": "#"
        },
        {
            "id": "16",
            "image": "https://cdn.hk01.com/media/article/86979/thumbnail/c89fa30bab50e5b8ca148e8c46b350db.jpg",
            "title": "將軍澳搗非法加油站　檢3000公升燃油　市值三萬",
            "preview": "消防處根據線報及深入調查，打擊非法燃油轉注特遣隊下午採取行動，於將軍澳至善街路邊搗破一個非法加油站。行動中發現一部第5類危險品車輛，即俗稱的油缸車，正為另一部車輛入油。人員撿獲3,……",
            "url": "#"
        },
        {
            "id": "17",
            "image": "https://cdn.hk01.com/media/article/86978/thumbnail/877f92eed3856a170acc8a1a16e75daa.jpg",
            "title": "海關督察當街摑人襲擊罪成　官：入小欖休息",
            "preview": "被告方富邦，43歲，現正停職，並無律師代表。他今到庭時更疑用手機拍攝記者，並在升降機出言侮辱記者，又在開庭前把疑在法院廁所內自拍的照片放上facebook。被告被裁定去年9月15日……",
            "url": "#"
        },
        {
            "id": "18",
            "image": "https://cdn.hk01.com/media/article/86971/thumbnail/f7cde81a5586552438ae3f7c02ad6ec3.jpg",
            "title": "【收市總結】恒指上漲122點　濠賭保險表現靚",
            "preview": "港股午後升幅放緩，濠賭及保險股成為升市主力。恒指收報24578點，上升122點；國指收報10317點，上升45點。成交額786億元。澳博勁升5.6%　新濠國際亦彈5.4%……",
            "url": "#"
        },
        {
            "id": "19",
            "image": "https://cdn.hk01.com/media/article/86940/thumbnail/60dc2dffe34fa06f801db61516d339bd.jpg",
            "title": "沙頭角尚澄享海景　平均呎售逾萬元　最貴定價逾千萬",
            "preview": "位於香港邊陲地區沙頭角區，事隔17年後再有私樓新盤登場，遠東發展旗下的尚澄今日（26日）開價，首批涉57伙價單折實平均呎價10,175元，入場費254萬元，最貴單位定價更逾千萬元。……",
            "url": "#"
        },
        {
            "id": "20",
            "image": "https://cdn.hk01.com/media/article/86898/thumbnail/d059c354c58c83a6cc18ba6c68d8f3d2.jpg",
            "title": "【迪士尼擴建．博評】財政黑洞——迪士尼和郵輪碼頭的共通之處",
            "preview": "政府沒有營商經驗卻被推到談判桌和變身商人，只因要完成長官意志，歷史一次又一次證明政府參予商業活動沒有好結果（壟斷生意例外）",
            "url": "#"
        }
    ]
}